<PAMDataset>
  <Metadata domain="IMAGE_STRUCTURE">
    <MDI key="COMPRESSION">JPEG</MDI>
    <MDI key="INTERLEAVE">PIXEL</MDI>
    <MDI key="SOURCE_COLOR_SPACE">YCbCr</MDI>
  </Metadata>
  <Metadata domain="xml:ESRI" format="xml">
    <GeodataXform xsi:type="typens:PolynomialXform" xmlns:xsi="http://www.w3.org/2001/XMLSchema-instance" xmlns:xs="http://www.w3.org/2001/XMLSchema" xmlns:typens="http://www.esri.com/schemas/ArcGIS/10.4">
      <PolynomialOrder>1</PolynomialOrder>
      <SpatialReference xsi:type="typens:ProjectedCoordinateSystem">
        <WKT>PROJCS["S-JTSK_Krovak_East_North",GEOGCS["GCS_S_JTSK",DATUM["D_S_JTSK",SPHEROID["Bessel_1841",6377397.155,299.1528128]],PRIMEM["Greenwich",0.0],UNIT["Degree",0.0174532925199433]],PROJECTION["Krovak"],PARAMETER["False_Easting",0.0],PARAMETER["False_Northing",0.0],PARAMETER["Pseudo_Standard_Parallel_1",78.5],PARAMETER["Scale_Factor",0.9999],PARAMETER["Azimuth",30.28813975277778],PARAMETER["Longitude_Of_Center",24.83333333333333],PARAMETER["Latitude_Of_Center",49.5],PARAMETER["X_Scale",-1.0],PARAMETER["Y_Scale",1.0],PARAMETER["XY_Plane_Rotation",90.0],UNIT["Meter",1.0],AUTHORITY["EPSG",5514]]</WKT>
        <XOrigin>-33699800</XOrigin>
        <YOrigin>-33699800</YOrigin>
        <XYScale>133638764.24698351</XYScale>
        <ZOrigin>-100000</ZOrigin>
        <ZScale>10000</ZScale>
        <MOrigin>-100000</MOrigin>
        <MScale>10000</MScale>
        <XYTolerance>0.001</XYTolerance>
        <ZTolerance>0.001</ZTolerance>
        <MTolerance>0.001</MTolerance>
        <HighPrecision>true</HighPrecision>
        <WKID>102067</WKID>
        <LatestWKID>5514</LatestWKID>
      </SpatialReference>
      <SourceGCPs xsi:type="typens:ArrayOfDouble">
        <Double>3728.9947392175673</Double>
        <Double>-1795.0518075441942</Double>
        <Double>2096.5778482834576</Double>
        <Double>-3538.1353798983619</Double>
        <Double>3728.3231197852874</Double>
        <Double>-6151.8259538840503</Double>
        <Double>3728.4787058415823</Double>
        <Double>-4336.7139517944306</Double>
        <Double>2050.664158303407</Double>
        <Double>-2044.9563450720161</Double>
        <Double>2538.1965745979687</Double>
        <Double>-6135.2472319453955</Double>
      </SourceGCPs>
      <TargetGCPs xsi:type="typens:ArrayOfDouble">
        <Double>-784466.193479985</Double>
        <Double>-1192714.1175067897</Double>
        <Double>-784919.72870000079</Double>
        <Double>-1193087.4945</Double>
        <Double>-784618.11270000041</Double>
        <Double>-1193779.0595999993</Double>
        <Double>-784554.7552307396</Double>
        <Double>-1193335.0706042107</Double>
        <Double>-784876.89660000056</Double>
        <Double>-1192721.1171999983</Double>
        <Double>-784905.68290000036</Double>
        <Double>-1193737.2569999993</Double>
      </TargetGCPs>
    </GeodataXform>
  </Metadata>
</PAMDataset>
