<PAMDataset>
  <SRS>PROJCS["S-JTSK_Krovak_East_North",GEOGCS["GCS_S_JTSK",DATUM["Jednotne_Trigonometricke_Site_Katastralni",SPHEROID["Bessel_1841",6377397.155,299.1528128]],PRIMEM["Greenwich",0.0],UNIT["Degree",0.0174532925199433]],PROJECTION["Krovak"],PARAMETER["False_Easting",0.0],PARAMETER["False_Northing",0.0],PARAMETER["Pseudo_Standard_Parallel_1",78.5],PARAMETER["Scale_Factor",0.9999],PARAMETER["Azimuth",30.28813975277778],PARAMETER["Longitude_Of_Center",24.83333333333333],PARAMETER["Latitude_Of_Center",49.5],PARAMETER["X_Scale",-1.0],PARAMETER["Y_Scale",1.0],PARAMETER["XY_Plane_Rotation",90.0],UNIT["Meter",1.0],AUTHORITY["EPSG","5514"]]</SRS>
  <Metadata domain="IMAGE_STRUCTURE">
    <MDI key="COMPRESSION">JPEG</MDI>
    <MDI key="INTERLEAVE">PIXEL</MDI>
    <MDI key="SOURCE_COLOR_SPACE">YCbCr</MDI>
  </Metadata>
  <Metadata domain="xml:ESRI" format="xml">
    <GeodataXform xsi:type="typens:CompositeXform" xmlns:xsi="http://www.w3.org/2001/XMLSchema-instance" xmlns:xs="http://www.w3.org/2001/XMLSchema" xmlns:typens="http://www.esri.com/schemas/ArcGIS/10.6">
      <XF_0 xsi:type="typens:ProjectiveXform">
        <SpatialReference xsi:type="typens:ProjectedCoordinateSystem">
          <WKT>PROJCS["S-JTSK_Krovak_East_North",GEOGCS["GCS_S_JTSK",DATUM["D_S_JTSK",SPHEROID["Bessel_1841",6377397.155,299.1528128]],PRIMEM["Greenwich",0.0],UNIT["Degree",0.0174532925199433]],PROJECTION["Krovak"],PARAMETER["False_Easting",0.0],PARAMETER["False_Northing",0.0],PARAMETER["Pseudo_Standard_Parallel_1",78.5],PARAMETER["Scale_Factor",0.9999],PARAMETER["Azimuth",30.28813975277778],PARAMETER["Longitude_Of_Center",24.83333333333333],PARAMETER["Latitude_Of_Center",49.5],PARAMETER["X_Scale",-1.0],PARAMETER["Y_Scale",1.0],PARAMETER["XY_Plane_Rotation",90.0],UNIT["Meter",1.0],AUTHORITY["EPSG",5514]]</WKT>
          <XOrigin>-33699800</XOrigin>
          <YOrigin>-33699800</YOrigin>
          <XYScale>133638764.24698351</XYScale>
          <ZOrigin>-100000</ZOrigin>
          <ZScale>10000</ZScale>
          <MOrigin>-100000</MOrigin>
          <MScale>10000</MScale>
          <XYTolerance>0.001</XYTolerance>
          <ZTolerance>0.001</ZTolerance>
          <MTolerance>0.001</MTolerance>
          <HighPrecision>true</HighPrecision>
          <WKID>102067</WKID>
          <LatestWKID>5514</LatestWKID>
        </SpatialReference>
        <SourceGCPs xsi:type="typens:ArrayOfDouble">
          <Double>5906.4252664026326</Double>
          <Double>-3953.2923171431544</Double>
          <Double>450.2848452195758</Double>
          <Double>-3978.8281105933711</Double>
          <Double>7613.6859869058244</Double>
          <Double>-2765.4471579212695</Double>
          <Double>2878.188334103208</Double>
          <Double>-3962.2782152341679</Double>
          <Double>3183.8419853687519</Double>
          <Double>-3960.9508703229949</Double>
          <Double>3487.018742917804</Double>
          <Double>-3959.6789701683447</Double>
          <Double>4996.5400554905646</Double>
          <Double>-236.01906894985586</Double>
          <Double>756.42456452769693</Double>
          <Double>-3977.5205896310508</Double>
          <Double>709.29133407492191</Double>
          <Double>-3975.6260914467275</Double>
          <Double>1365.655559499166</Double>
          <Double>-3972.4002811415121</Double>
          <Double>4396.9348978708731</Double>
          <Double>-3956.5401657763869</Double>
          <Double>5002.7628610797692</Double>
          <Double>-3954.3558672275394</Double>
          <Double>4697.8862795317546</Double>
          <Double>-3954.8908189414069</Double>
          <Double>6006.2423401344568</Double>
          <Double>-2992.4249964412302</Double>
          <Double>2757.3521236816887</Double>
          <Double>-1342.1817679433152</Double>
          <Double>2202.1251705137547</Double>
          <Double>-1850.5185069069266</Double>
          <Double>4091.9183389777318</Double>
          <Double>-3957.8393376627937</Double>
          <Double>3784.5603436165256</Double>
          <Double>-3958.3048029448837</Double>
          <Double>2575.0040420605801</Double>
          <Double>-3963.5629984550178</Double>
          <Double>2272.100339183351</Double>
          <Double>-3966.0411523319781</Double>
          <Double>1967.2981744710123</Double>
          <Double>-3968.1523237228394</Double>
          <Double>1659.5786786864046</Double>
          <Double>-3970.4028133768588</Double>
          <Double>1059.3233791054226</Double>
          <Double>-3974.2643606811762</Double>
          <Double>5906.4539975607768</Double>
          <Double>-3049.4064611010253</Double>
          <Double>5907.0657019190257</Double>
          <Double>-3337.3667749203742</Double>
          <Double>6553.2061420431128</Double>
          <Double>-725.12564589548856</Double>
        </SourceGCPs>
        <TargetGCPs xsi:type="typens:ArrayOfDouble">
          <Double>-760660.28657720971</Double>
          <Double>-1092975.1514451061</Double>
          <Double>-762012.10772844404</Double>
          <Double>-1092782.3124350293</Double>
          <Double>-760197.77479999885</Double>
          <Double>-1092747.8396000005</Double>
          <Double>-761411.30261189409</Double>
          <Double>-1092868.0130544163</Double>
          <Double>-761336.20118157461</Double>
          <Double>-1092878.7269146163</Double>
          <Double>-761261.0997140645</Double>
          <Double>-1092889.4407728272</Double>
          <Double>-760768.35970000178</Double>
          <Double>-1092032.4836000018</Double>
          <Double>-761937.00734256592</Double>
          <Double>-1092793.0244162467</Double>
          <Double>-761949.59523732984</Double>
          <Double>-1092791.2365866352</Double>
          <Double>-761786.80659238051</Double>
          <Double>-1092814.4485260842</Double>
          <Double>-761035.79508409323</Double>
          <Double>-1092921.5823247891</Double>
          <Double>-760885.59180275933</Double>
          <Double>-1092943.0099971611</Double>
          <Double>-760960.69346326916</Double>
          <Double>-1092932.2961644935</Double>
          <Double>-760602.69345585909</Double>
          <Double>-1092743.467105</Double>
          <Double>-761355.38064039417</Double>
          <Double>-1092221.6802715808</Double>
          <Double>-761510.440200001</Double>
          <Double>-1092320.4692000002</Double>
          <Double>-761110.8966658084</Double>
          <Double>-1092910.8684789548</Double>
          <Double>-761185.9982089625</Double>
          <Double>-1092900.1546279606</Double>
          <Double>-761486.40400536102</Double>
          <Double>-1092857.2991933322</Double>
          <Double>-761561.50536224397</Double>
          <Double>-1092846.5853324784</Double>
          <Double>-761636.60587799316</Double>
          <Double>-1092835.8728283411</Double>
          <Double>-761711.70623022737</Double>
          <Double>-1092825.1606535115</Double>
          <Double>-761861.9069635045</Double>
          <Double>-1092803.736446782</Double>
          <Double>-760628.78871660819</Double>
          <Double>-1092754.3504875686</Double>
          <Double>-760638.86387481552</Double>
          <Double>-1092824.9543445075</Double>
          <Double>-760384.08098409034</Double>
          <Double>-1092207.1654730376</Double>
        </TargetGCPs>
      </XF_0>
      <XF_1 xsi:type="typens:PolynomialXform">
        <PolynomialOrder>1</PolynomialOrder>
        <SpatialReference xsi:type="typens:ProjectedCoordinateSystem">
          <WKT>PROJCS["S-JTSK_Krovak_East_North",GEOGCS["GCS_S_JTSK",DATUM["D_S_JTSK",SPHEROID["Bessel_1841",6377397.155,299.1528128]],PRIMEM["Greenwich",0.0],UNIT["Degree",0.0174532925199433]],PROJECTION["Krovak"],PARAMETER["False_Easting",0.0],PARAMETER["False_Northing",0.0],PARAMETER["Pseudo_Standard_Parallel_1",78.5],PARAMETER["Scale_Factor",0.9999],PARAMETER["Azimuth",30.28813975277778],PARAMETER["Longitude_Of_Center",24.83333333333333],PARAMETER["Latitude_Of_Center",49.5],PARAMETER["X_Scale",-1.0],PARAMETER["Y_Scale",1.0],PARAMETER["XY_Plane_Rotation",90.0],UNIT["Meter",1.0],AUTHORITY["EPSG",5514]]</WKT>
          <XOrigin>-33699800</XOrigin>
          <YOrigin>-33699800</YOrigin>
          <XYScale>133638764.24698351</XYScale>
          <ZOrigin>-100000</ZOrigin>
          <ZScale>10000</ZScale>
          <MOrigin>-100000</MOrigin>
          <MScale>10000</MScale>
          <XYTolerance>0.001</XYTolerance>
          <ZTolerance>0.001</ZTolerance>
          <MTolerance>0.001</MTolerance>
          <HighPrecision>true</HighPrecision>
          <WKID>102067</WKID>
          <LatestWKID>5514</LatestWKID>
        </SpatialReference>
        <SourceGCPs xsi:type="typens:ArrayOfDouble">
          <Double>-761511.38095795643</Double>
          <Double>-1092324.7100091185</Double>
          <Double>-761504.14599715907</Double>
          <Double>-1092266.7202624741</Double>
          <Double>-761490.56740754913</Double>
          <Double>-1092244.1687348215</Double>
          <Double>-761430.31441912532</Double>
          <Double>-1092266.2254753283</Double>
          <Double>-761415.32066047203</Double>
          <Double>-1092210.0997005631</Double>
          <Double>-761336.18806466239</Double>
          <Double>-1092224.8216562723</Double>
          <Double>-761144.67686506372</Double>
          <Double>-1092353.068610392</Double>
          <Double>-760970.66544409213</Double>
          <Double>-1092263.7532708894</Double>
          <Double>-761124.50776765845</Double>
          <Double>-1092244.3097757895</Double>
          <Double>-760938.80169964943</Double>
          <Double>-1092142.2485396864</Double>
          <Double>-760894.7767457423</Double>
          <Double>-1092085.6146206041</Double>
          <Double>-760762.06349206797</Double>
          <Double>-1092029.762863735</Double>
          <Double>-760754.27845117229</Double>
          <Double>-1092155.7512495685</Double>
          <Double>-760729.63110380608</Double>
          <Double>-1092129.7923862753</Double>
          <Double>-760631.61833517475</Double>
          <Double>-1092108.1579608521</Double>
          <Double>-760546.63513827219</Double>
          <Double>-1092141.3572600025</Double>
          <Double>-760349.03206709202</Double>
          <Double>-1092183.3857111309</Double>
          <Double>-760660.30372908665</Double>
          <Double>-1092976.0132540837</Double>
          <Double>-761948.65193619428</Double>
          <Double>-1092791.6084796812</Double>
          <Double>-761908.07387838594</Double>
          <Double>-1092778.8806110853</Double>
          <Double>-761707.92365956749</Double>
          <Double>-1092802.0070521284</Double>
          <Double>-761703.28736154095</Double>
          <Double>-1092791.0174530463</Double>
          <Double>-761683.93573936156</Double>
          <Double>-1092789.2781874586</Double>
          <Double>-761660.2229262162</Double>
          <Double>-1092617.4098346867</Double>
          <Double>-761594.65910237469</Double>
          <Double>-1092497.0530303745</Double>
          <Double>-760942.0375546962</Double>
          <Double>-1092934.6204597801</Double>
          <Double>-761926.74222776049</Double>
          <Double>-1092794.6300848774</Double>
          <Double>-761687.96537591948</Double>
          <Double>-1092827.9751119064</Double>
          <Double>-761684.11967959162</Double>
          <Double>-1092828.6284797736</Double>
        </SourceGCPs>
        <TargetGCPs xsi:type="typens:ArrayOfDouble">
          <Double>-761505.89200000092</Double>
          <Double>-1092325.2934999987</Double>
          <Double>-761497.6528000012</Double>
          <Double>-1092265.6807000004</Double>
          <Double>-761485.50840000063</Double>
          <Double>-1092242.5826000012</Double>
          <Double>-761424.7864000015</Double>
          <Double>-1092265.6013999991</Double>
          <Double>-761408.51449999958</Double>
          <Double>-1092211.8643999994</Double>
          <Double>-761328.98059999943</Double>
          <Double>-1092226.7074999996</Double>
          <Double>-761138.95650000125</Double>
          <Double>-1092354.8189999983</Double>
          <Double>-760966.23620000109</Double>
          <Double>-1092264.7281999998</Double>
          <Double>-761116.96959999949</Double>
          <Double>-1092245.3607000001</Double>
          <Double>-760934.00979999825</Double>
          <Double>-1092142.4111000001</Double>
          <Double>-760889.00409999862</Double>
          <Double>-1092087.9598000012</Double>
          <Double>-760757.87640000135</Double>
          <Double>-1092032.1590000018</Double>
          <Double>-760751.03819999844</Double>
          <Double>-1092157.5254999995</Double>
          <Double>-760725.96889999881</Double>
          <Double>-1092131.0670999996</Double>
          <Double>-760628.80040000007</Double>
          <Double>-1092111.3555999994</Double>
          <Double>-760542.54610000178</Double>
          <Double>-1092143.5687000006</Double>
          <Double>-760345.32250000164</Double>
          <Double>-1092183.3795000017</Double>
          <Double>-760660.28657720971</Double>
          <Double>-1092975.1514451061</Double>
          <Double>-761950.14286817703</Double>
          <Double>-1092789.120457995</Double>
          <Double>-761909.3175781949</Double>
          <Double>-1092776.7489575583</Double>
          <Double>-761707.30146018276</Double>
          <Double>-1092799.4359213361</Double>
          <Double>-761702.85512837279</Double>
          <Double>-1092788.7930354651</Double>
          <Double>-761684.12589820509</Double>
          <Double>-1092786.8218856892</Double>
          <Double>-761658.14376290725</Double>
          <Double>-1092615.9448078158</Double>
          <Double>-761591.03581445245</Double>
          <Double>-1092494.1459418177</Double>
          <Double>-760943.26377035142</Double>
          <Double>-1092934.1050753105</Double>
          <Double>-761926.62428424507</Double>
          <Double>-1092793.2013333342</Double>
          <Double>-761686.32445677777</Double>
          <Double>-1092827.1970991076</Double>
          <Double>-761683.05796115275</Double>
          <Double>-1092827.6671898214</Double>
        </TargetGCPs>
        <Name />
      </XF_1>
      <RequireDEM>false</RequireDEM>
    </GeodataXform>
  </Metadata>
</PAMDataset>
