<PAMDataset>
  <SRS>PROJCS["S-JTSK_Krovak_East_North",GEOGCS["GCS_S_JTSK",DATUM["Jednotne_Trigonometricke_Site_Katastralni",SPHEROID["Bessel_1841",6377397.155,299.1528128]],PRIMEM["Greenwich",0.0],UNIT["Degree",0.0174532925199433]],PROJECTION["Krovak"],PARAMETER["False_Easting",0.0],PARAMETER["False_Northing",0.0],PARAMETER["Pseudo_Standard_Parallel_1",78.5],PARAMETER["Scale_Factor",0.9999],PARAMETER["Azimuth",30.28813975277778],PARAMETER["Longitude_Of_Center",24.83333333333333],PARAMETER["Latitude_Of_Center",49.5],PARAMETER["X_Scale",-1.0],PARAMETER["Y_Scale",1.0],PARAMETER["XY_Plane_Rotation",90.0],UNIT["Meter",1.0],AUTHORITY["EPSG","5514"]]</SRS>
  <Metadata domain="IMAGE_STRUCTURE">
    <MDI key="COMPRESSION">JPEG</MDI>
    <MDI key="INTERLEAVE">PIXEL</MDI>
    <MDI key="SOURCE_COLOR_SPACE">YCbCr</MDI>
  </Metadata>
  <Metadata domain="xml:ESRI" format="xml">
    <GeodataXform xsi:type="typens:PolynomialXform" xmlns:xsi="http://www.w3.org/2001/XMLSchema-instance" xmlns:xs="http://www.w3.org/2001/XMLSchema" xmlns:typens="http://www.esri.com/schemas/ArcGIS/10.6">
      <PolynomialOrder>1</PolynomialOrder>
      <SpatialReference xsi:type="typens:ProjectedCoordinateSystem">
        <WKT>PROJCS["S-JTSK_Krovak_East_North",GEOGCS["GCS_S_JTSK",DATUM["D_S_JTSK",SPHEROID["Bessel_1841",6377397.155,299.1528128]],PRIMEM["Greenwich",0.0],UNIT["Degree",0.0174532925199433]],PROJECTION["Krovak"],PARAMETER["False_Easting",0.0],PARAMETER["False_Northing",0.0],PARAMETER["Pseudo_Standard_Parallel_1",78.5],PARAMETER["Scale_Factor",0.9999],PARAMETER["Azimuth",30.28813975277778],PARAMETER["Longitude_Of_Center",24.83333333333333],PARAMETER["Latitude_Of_Center",49.5],PARAMETER["X_Scale",-1.0],PARAMETER["Y_Scale",1.0],PARAMETER["XY_Plane_Rotation",90.0],UNIT["Meter",1.0],AUTHORITY["EPSG",5514]]</WKT>
        <XOrigin>-33699800</XOrigin>
        <YOrigin>-33699800</YOrigin>
        <XYScale>133638764.24698351</XYScale>
        <ZOrigin>-100000</ZOrigin>
        <ZScale>10000</ZScale>
        <MOrigin>-100000</MOrigin>
        <MScale>10000</MScale>
        <XYTolerance>0.001</XYTolerance>
        <ZTolerance>0.001</ZTolerance>
        <MTolerance>0.001</MTolerance>
        <HighPrecision>true</HighPrecision>
        <WKID>102067</WKID>
        <LatestWKID>5514</LatestWKID>
      </SpatialReference>
      <SourceGCPs xsi:type="typens:ArrayOfDouble">
        <Double>1969.2983121691504</Double>
        <Double>-1692.0302998414263</Double>
        <Double>276.1254528457066</Double>
        <Double>-969.86318171303719</Double>
        <Double>266.44338824425358</Double>
        <Double>-1505.5101872030646</Double>
        <Double>260.21792799641844</Double>
        <Double>-1889.6658660359681</Double>
        <Double>563.3317177669378</Double>
        <Double>-1941.2969146799296</Double>
        <Double>762.02363246993627</Double>
        <Double>-1930.5039792796597</Double>
        <Double>1077.9917317442596</Double>
        <Double>-1937.204811415635</Double>
      </SourceGCPs>
      <TargetGCPs xsi:type="typens:ArrayOfDouble">
        <Double>-760121.46119999886</Double>
        <Double>-1092152.6570999995</Double>
        <Double>-760507.33320000023</Double>
        <Double>-1091917.6044000015</Double>
        <Double>-760526.92493305425</Double>
        <Double>-1092049.4664102215</Double>
        <Double>-760540.9721999988</Double>
        <Double>-1092144.0681999996</Double>
        <Double>-760469.80803049449</Double>
        <Double>-1092167.7891778387</Double>
        <Double>-760427.32909136056</Double>
        <Double>-1092172.7545349931</Double>
        <Double>-760346.08902992681</Double>
        <Double>-1092185.1018256873</Double>
      </TargetGCPs>
      <Name />
    </GeodataXform>
  </Metadata>
</PAMDataset>
